<Gff Version="1" Type="GIT">
    <Struct Name="AreaProperties" Id="100">
        <Int Name="AmbientSndDay">51</Int>
        <Int Name="AmbientSndDayVol">32</Int>
        <Int Name="AmbientSndNight">51</Int>
        <Int Name="AmbientSndNitVol">32</Int>
        <Int Name="EnvAudio">89</Int>
        <Int Name="MusicBattle">34</Int>
        <Int Name="MusicDay">1</Int>
        <Int Name="MusicDelay">90000</Int>
        <Int Name="MusicNight">3</Int>
    </Struct>
    <List Name="Creature List"/>
    <List Name="Door List">
        <Struct Id="8">
            <Byte Name="AnimationState">1</Byte>
            <DWord Name="Appearance">57</DWord>
            <Byte Name="AutoRemoveKey">0</Byte>
            <Float Name="Bearing">-1.570794</Float>
            <Byte Name="CloseLockDC">0</Byte>
            <ResRef Name="Conversation"></ResRef>
            <Short Name="CurrentHP">80</Short>
            <CExoLocString Name="Description">
                <DWord Name="StringRef">4294967295</DWord>
            </CExoLocString>
            <Byte Name="DisarmDC">15</Byte>
            <DWord Name="Faction">1</DWord>
            <Byte Name="Fort">16</Byte>
            <Byte Name="GenericType">0</Byte>
            <Short Name="HP">80</Short>
            <Byte Name="Hardness">5</Byte>
            <Byte Name="Interruptable">1</Byte>
            <CExoString Name="KeyName"></CExoString>
            <Byte Name="KeyRequired">0</Byte>
            <CExoString Name="LinkedTo">KrillanToPlains</CExoString>
            <Byte Name="LinkedToFlags">1</Byte>
            <Word Name="LoadScreenID">0</Word>
            <CExoLocString Name="LocName">
                <DWord Name="StringRef">5349</DWord>
                <SubString>
                    <Int Name="StringID">0</Int>
                    <CExoString Name="String">PlainsToKrillan</CExoString>
                </SubString>
            </CExoLocString>
            <Byte Name="Lockable">0</Byte>
            <Byte Name="Locked">0</Byte>
            <ResRef Name="OnClick"></ResRef>
            <ResRef Name="OnClosed"></ResRef>
            <ResRef Name="OnDamaged"></ResRef>
            <ResRef Name="OnDeath"></ResRef>
            <ResRef Name="OnDisarm"></ResRef>
            <ResRef Name="OnFailToOpen"></ResRef>
            <ResRef Name="OnHeartbeat"></ResRef>
            <ResRef Name="OnLock"></ResRef>
            <ResRef Name="OnMeleeAttacked"></ResRef>
            <ResRef Name="OnOpen"></ResRef>
            <ResRef Name="OnSpellCastAt"></ResRef>
            <ResRef Name="OnTrapTriggered"></ResRef>
            <ResRef Name="OnUnlock"></ResRef>
            <ResRef Name="OnUserDefined"></ResRef>
            <Byte Name="OpenLockDC">18</Byte>
            <Byte Name="Plot">0</Byte>
            <Word Name="PortraitId">0</Word>
            <Byte Name="Ref">0</Byte>
            <CExoString Name="Tag">PlainsToKrillan</CExoString>
            <ResRef Name="TemplateResRef">nw_door_ttr_12</ResRef>
            <Byte Name="TrapDetectDC">0</Byte>
            <Byte Name="TrapDetectable">1</Byte>
            <Byte Name="TrapDisarmable">1</Byte>
            <Byte Name="TrapFlag">0</Byte>
            <Byte Name="TrapOneShot">1</Byte>
            <Byte Name="TrapType">0</Byte>
            <Byte Name="Will">0</Byte>
            <Float Name="X">154.509995</Float>
            <Float Name="Y">125.260002</Float>
            <Float Name="Z">-0.440000</Float>
        </Struct>
        <Struct Id="8">
            <Byte Name="AnimationState">1</Byte>
            <DWord Name="Appearance">65</DWord>
            <Byte Name="AutoRemoveKey">0</Byte>
            <Float Name="Bearing">-3.141572</Float>
            <Byte Name="CloseLockDC">0</Byte>
            <CExoString Name="Comment"></CExoString>
            <ResRef Name="Conversation"></ResRef>
            <Short Name="CurrentHP">80</Short>
            <CExoLocString Name="Description">
                <DWord Name="StringRef">4294967295</DWord>
            </CExoLocString>
            <Byte Name="DisarmDC">15</Byte>
            <DWord Name="Faction">1</DWord>
            <Byte Name="Fort">16</Byte>
            <Byte Name="GenericType">0</Byte>
            <Short Name="HP">80</Short>
            <Byte Name="Hardness">5</Byte>
            <Byte Name="Interruptable">1</Byte>
            <CExoString Name="KeyName"></CExoString>
            <Byte Name="KeyRequired">0</Byte>
            <CExoString Name="LinkedTo">WP_CleavenRuinsToPlains</CExoString>
            <Byte Name="LinkedToFlags">2</Byte>
            <Word Name="LoadScreenID">0</Word>
            <CExoLocString Name="LocName">
                <DWord Name="StringRef">5349</DWord>
                <SubString>
                    <Int Name="StringID">0</Int>
                    <CExoString Name="String">PlainsToCleavenRuins</CExoString>
                </SubString>
            </CExoLocString>
            <Byte Name="Lockable">0</Byte>
            <Byte Name="Locked">0</Byte>
            <ResRef Name="OnClick"></ResRef>
            <ResRef Name="OnClosed"></ResRef>
            <ResRef Name="OnDamaged"></ResRef>
            <ResRef Name="OnDeath"></ResRef>
            <ResRef Name="OnDisarm"></ResRef>
            <ResRef Name="OnFailToOpen"></ResRef>
            <ResRef Name="OnHeartbeat"></ResRef>
            <ResRef Name="OnLock"></ResRef>
            <ResRef Name="OnMeleeAttacked"></ResRef>
            <ResRef Name="OnOpen"></ResRef>
            <ResRef Name="OnSpellCastAt"></ResRef>
            <ResRef Name="OnTrapTriggered"></ResRef>
            <ResRef Name="OnUnlock"></ResRef>
            <ResRef Name="OnUserDefined"></ResRef>
            <Byte Name="OpenLockDC">18</Byte>
            <Byte Name="Plot">0</Byte>
            <Word Name="PortraitId">0</Word>
            <Byte Name="Ref">0</Byte>
            <CExoString Name="Tag">PlainsToCleavenRuins</CExoString>
            <ResRef Name="TemplateResRef">nw_door_ttr_29</ResRef>
            <Byte Name="TrapDetectDC">0</Byte>
            <Byte Name="TrapDetectable">1</Byte>
            <Byte Name="TrapDisarmable">1</Byte>
            <Byte Name="TrapFlag">0</Byte>
            <Byte Name="TrapOneShot">1</Byte>
            <Byte Name="TrapType">0</Byte>
            <Byte Name="Will">0</Byte>
            <Float Name="X">55.000000</Float>
            <Float Name="Y">1.810000</Float>
            <Float Name="Z">0.000000</Float>
        </Struct>
    </List>
    <List Name="Encounter List">
        <Struct Id="7">
            <Byte Name="Active">1</Byte>
            <CExoString Name="Comment"></CExoString>
            <List Name="CreatureList">
                <Struct Id="0">
                    <Int Name="Appearance">185</Int>
                    <Float Name="CR">3.000000</Float>
                    <CExoString Name="Comment"></CExoString>
                    <ResRef Name="ResRef">cnraworg</ResRef>
                    <Byte Name="SingleSpawn">0</Byte>
                </Struct>
                <Struct Id="0">
                    <Int Name="Appearance">175</Int>
                    <Float Name="CR">5.000000</Float>
                    <CExoString Name="Comment"></CExoString>
                    <ResRef Name="ResRef">nw_direwolf</ResRef>
                    <Byte Name="SingleSpawn">0</Byte>
                </Struct>
                <Struct Id="0">
                    <Int Name="Appearance">175</Int>
                    <Float Name="CR">11.000000</Float>
                    <CExoString Name="Comment"></CExoString>
                    <ResRef Name="ResRef">nw_wolfdireboss</ResRef>
                    <Byte Name="SingleSpawn">0</Byte>
                </Struct>
            </List>
            <Int Name="Difficulty">0</Int>
            <Int Name="DifficultyIndex">3</Int>
            <DWord Name="Faction">1</DWord>
            <List Name="Geometry">
                <Struct Id="1">
                    <CExoString Name="Comment"></CExoString>
                    <Float Name="X">-0.000016</Float>
                    <Float Name="Y">-0.221001</Float>
                    <Float Name="Z">0.025000</Float>
                </Struct>
                <Struct Id="1">
                    <Float Name="X">60.109989</Float>
                    <Float Name="Y">-24.972168</Float>
                    <Float Name="Z">0.025000</Float>
                </Struct>
                <Struct Id="1">
                    <Float Name="X">45.303474</Float>
                    <Float Name="Y">-24.972178</Float>
                    <Float Name="Z">0.025000</Float>
                </Struct>
                <Struct Id="1">
                    <Float Name="X">45.303478</Float>
                    <Float Name="Y">-38.010738</Float>
                    <Float Name="Z">0.025000</Float>
                </Struct>
                <Struct Id="1">
                    <Float Name="X">63.368492</Float>
                    <Float Name="Y">-37.423882</Float>
                    <Float Name="Z">0.025000</Float>
                </Struct>
                <Struct Id="1">
                    <Float Name="X">63.203888</Float>
                    <Float Name="Y">-24.972168</Float>
                    <Float Name="Z">0.025000</Float>
                </Struct>
                <Struct Id="1">
                    <Float Name="X">20.331312</Float>
                    <Float Name="Y">5.082825</Float>
                    <Float Name="Z">0.025001</Float>
                </Struct>
                <Struct Id="1">
                    <Float Name="X">20.331310</Float>
                    <Float Name="Y">94.805847</Float>
                    <Float Name="Z">0.025000</Float>
                </Struct>
                <Struct Id="1">
                    <Float Name="X">96.794762</Float>
                    <Float Name="Y">102.761566</Float>
                    <Float Name="Z">0.025001</Float>
                </Struct>
                <Struct Id="1">
                    <Float Name="X">109.170708</Float>
                    <Float Name="Y">102.762314</Float>
                    <Float Name="Z">0.022560</Float>
                </Struct>
                <Struct Id="1">
                    <Float Name="X">143.645218</Float>
                    <Float Name="Y">85.745132</Float>
                    <Float Name="Z">0.025000</Float>
                </Struct>
                <Struct Id="1">
                    <Float Name="X">143.645218</Float>
                    <Float Name="Y">78.010406</Float>
                    <Float Name="Z">0.025000</Float>
                </Struct>
                <Struct Id="1">
                    <Float Name="X">152.263931</Float>
                    <Float Name="Y">78.010406</Float>
                    <Float Name="Z">0.025000</Float>
                </Struct>
                <Struct Id="1">
                    <Float Name="X">152.263901</Float>
                    <Float Name="Y">88.176056</Float>
                    <Float Name="Z">0.025000</Float>
                </Struct>
                <Struct Id="1">
                    <Float Name="X">142.982254</Float>
                    <Float Name="Y">88.176056</Float>
                    <Float Name="Z">0.025001</Float>
                </Struct>
                <Struct Id="1">
                    <Float Name="X">111.159668</Float>
                    <Float Name="Y">104.309280</Float>
                    <Float Name="Z">0.022560</Float>
                </Struct>
                <Struct Id="1">
                    <Float Name="X">111.159286</Float>
                    <Float Name="Y">115.137161</Float>
                    <Float Name="Z">0.025000</Float>
                </Struct>
                <Struct Id="1">
                    <Float Name="X">95.910995</Float>
                    <Float Name="Y">115.138031</Float>
                    <Float Name="Z">0.022560</Float>
                </Struct>
                <Struct Id="1">
                    <Float Name="X">95.910805</Float>
                    <Float Name="Y">104.750504</Float>
                    <Float Name="Z">0.025000</Float>
                </Struct>
                <Struct Id="1">
                    <Float Name="X">19.226351</Float>
                    <Float Name="Y">97.236755</Float>
                    <Float Name="Z">0.025000</Float>
                </Struct>
                <Struct Id="1">
                    <Float Name="X">-0.000006</Float>
                    <Float Name="Y">97.236755</Float>
                    <Float Name="Z">0.025001</Float>
                </Struct>
                <Struct Id="1">
                    <Float Name="X">0.000000</Float>
                    <Float Name="Y">0.000000</Float>
                    <Float Name="Z">0.025001</Float>
                </Struct>
            </List>
            <CExoLocString Name="LocalizedName">
                <DWord Name="StringRef">4294967295</DWord>
                <SubString>
                    <Int Name="StringID">0</Int>
                    <CExoString Name="String">Canine Encounter</CExoString>
                </SubString>
            </CExoLocString>
            <Int Name="MaxCreatures">2</Int>
            <ResRef Name="OnEntered"></ResRef>
            <ResRef Name="OnExhausted"></ResRef>
            <ResRef Name="OnExit"></ResRef>
            <ResRef Name="OnHeartbeat"></ResRef>
            <ResRef Name="OnUserDefined"></ResRef>
            <Byte Name="PlayerOnly">1</Byte>
            <Int Name="RecCreatures">1</Int>
            <Byte Name="Reset">1</Byte>
            <Int Name="ResetTime">1200</Int>
            <Int Name="Respawns">-1</Int>
            <Int Name="SpawnOption">0</Int>
            <List Name="SpawnPointList">
                <Struct Id="2">
                    <Float Name="Orientation">-0.000000</Float>
                    <Float Name="X">128.762070</Float>
                    <Float Name="Y">100.343361</Float>
                    <Float Name="Z">0.000010</Float>
                </Struct>
            </List>
            <CExoString Name="Tag">CanineEncounter</CExoString>
            <ResRef Name="TemplateResRef">canineencounter</ResRef>
            <Float Name="XPosition">1.216132</Float>
            <Float Name="YPosition">41.768276</Float>
            <Float Name="ZPosition">0.000000</Float>
        </Struct>
        <Struct Id="7">
            <Byte Name="Active">1</Byte>
            <List Name="CreatureList">
                <Struct Id="0">
                    <Int Name="Appearance">35</Int>
                    <Float Name="CR">0.333333</Float>
                    <ResRef Name="ResRef">cnradeer</ResRef>
                    <Byte Name="SingleSpawn">0</Byte>
                </Struct>
                <Struct Id="0">
                    <Int Name="Appearance">37</Int>
                    <Float Name="CR">0.333333</Float>
                    <ResRef Name="ResRef">cnrawhitestag</ResRef>
                    <Byte Name="SingleSpawn">0</Byte>
                </Struct>
                <Struct Id="0">
                    <Int Name="Appearance">8</Int>
                    <Float Name="CR">0.500000</Float>
                    <ResRef Name="ResRef">cnrabadger</ResRef>
                    <Byte Name="SingleSpawn">0</Byte>
                </Struct>
                <Struct Id="0">
                    <Int Name="Appearance">12</Int>
                    <Float Name="CR">2.000000</Float>
                    <ResRef Name="ResRef">cnrablkbear</ResRef>
                    <Byte Name="SingleSpawn">0</Byte>
                </Struct>
                <Struct Id="0">
                    <Int Name="Appearance">21</Int>
                    <Float Name="CR">2.000000</Float>
                    <ResRef Name="ResRef">cnraboar</ResRef>
                    <Byte Name="SingleSpawn">0</Byte>
                </Struct>
                <Struct Id="0">
                    <Int Name="Appearance">203</Int>
                    <Float Name="CR">2.000000</Float>
                    <ResRef Name="ResRef">cnracougar</ResRef>
                    <Byte Name="SingleSpawn">0</Byte>
                </Struct>
                <Struct Id="0">
                    <Int Name="Appearance">94</Int>
                    <Float Name="CR">2.000000</Float>
                    <ResRef Name="ResRef">cnracragcat</ResRef>
                    <Byte Name="SingleSpawn">0</Byte>
                </Struct>
                <Struct Id="0">
                    <Int Name="Appearance">96</Int>
                    <Float Name="CR">2.000000</Float>
                    <ResRef Name="ResRef">nw_krenshar</ResRef>
                    <Byte Name="SingleSpawn">0</Byte>
                </Struct>
                <Struct Id="0">
                    <Int Name="Appearance">93</Int>
                    <Float Name="CR">2.000000</Float>
                    <ResRef Name="ResRef">cnraleopard</ResRef>
                    <Byte Name="SingleSpawn">0</Byte>
                </Struct>
                <Struct Id="0">
                    <Int Name="Appearance">202</Int>
                    <Float Name="CR">2.000000</Float>
                    <ResRef Name="ResRef">cnrapanther</ResRef>
                    <Byte Name="SingleSpawn">0</Byte>
                </Struct>
                <Struct Id="0">
                    <Int Name="Appearance">98</Int>
                    <Float Name="CR">3.000000</Float>
                    <ResRef Name="ResRef">cnrajaguar</ResRef>
                    <Byte Name="SingleSpawn">0</Byte>
                </Struct>
                <Struct Id="0">
                    <Int Name="Appearance">97</Int>
                    <Float Name="CR">3.000000</Float>
                    <ResRef Name="ResRef">cnralion</ResRef>
                    <Byte Name="SingleSpawn">0</Byte>
                </Struct>
                <Struct Id="0">
                    <Int Name="Appearance">13</Int>
                    <Float Name="CR">5.000000</Float>
                    <ResRef Name="ResRef">cnrabrnbear</ResRef>
                    <Byte Name="SingleSpawn">0</Byte>
                </Struct>
                <Struct Id="0">
                    <Int Name="Appearance">175</Int>
                    <Float Name="CR">5.000000</Float>
                    <ResRef Name="ResRef">nw_direwolf</ResRef>
                    <Byte Name="SingleSpawn">0</Byte>
                </Struct>
                <Struct Id="0">
                    <Int Name="Appearance">204</Int>
                    <Float Name="CR">6.000000</Float>
                    <ResRef Name="ResRef">cnragrizbear</ResRef>
                    <Byte Name="SingleSpawn">0</Byte>
                </Struct>
            </List>
            <Int Name="Difficulty">0</Int>
            <Int Name="DifficultyIndex">3</Int>
            <DWord Name="Faction">1</DWord>
            <List Name="Geometry">
                <Struct Id="1">
                    <Float Name="X">0.000000</Float>
                    <Float Name="Y">0.000000</Float>
                    <Float Name="Z">0.025000</Float>
                </Struct>
                <Struct Id="1">
                    <Float Name="X">0.825239</Float>
                    <Float Name="Y">0.000008</Float>
                    <Float Name="Z">0.025000</Float>
                </Struct>
                <Struct Id="1">
                    <Float Name="X">59.416504</Float>
                    <Float Name="Y">-24.206718</Float>
                    <Float Name="Z">0.025001</Float>
                </Struct>
                <Struct Id="1">
                    <Float Name="X">44.837456</Float>
                    <Float Name="Y">-23.931644</Float>
                    <Float Name="Z">0.025001</Float>
                </Struct>
                <Struct Id="1">
                    <Float Name="X">45.228554</Float>
                    <Float Name="Y">-37.765427</Float>
                    <Float Name="Z">0.025000</Float>
                </Struct>
                <Struct Id="1">
                    <Float Name="X">63.412926</Float>
                    <Float Name="Y">-37.613541</Float>
                    <Float Name="Z">4.025000</Float>
                </Struct>
                <Struct Id="1">
                    <Float Name="X">62.992493</Float>
                    <Float Name="Y">-23.656569</Float>
                    <Float Name="Z">0.025000</Float>
                </Struct>
                <Struct Id="1">
                    <Float Name="X">20.630730</Float>
                    <Float Name="Y">5.501530</Float>
                    <Float Name="Z">0.025000</Float>
                </Struct>
                <Struct Id="1">
                    <Float Name="X">20.080578</Float>
                    <Float Name="Y">95.726578</Float>
                    <Float Name="Z">0.025000</Float>
                </Struct>
                <Struct Id="1">
                    <Float Name="X">96.276741</Float>
                    <Float Name="Y">103.978882</Float>
                    <Float Name="Z">0.025001</Float>
                </Struct>
                <Struct Id="1">
                    <Float Name="X">108.930420</Float>
                    <Float Name="Y">103.704391</Float>
                    <Float Name="Z">0.022560</Float>
                </Struct>
                <Struct Id="1">
                    <Float Name="X">143.589890</Float>
                    <Float Name="Y">86.098900</Float>
                    <Float Name="Z">0.025000</Float>
                </Struct>
                <Struct Id="1">
                    <Float Name="X">143.864975</Float>
                    <Float Name="Y">78.671860</Float>
                    <Float Name="Z">0.025000</Float>
                </Struct>
                <Struct Id="1">
                    <Float Name="X">152.392349</Float>
                    <Float Name="Y">78.671844</Float>
                    <Float Name="Z">0.025000</Float>
                </Struct>
                <Struct Id="1">
                    <Float Name="X">152.116547</Float>
                    <Float Name="Y">89.124176</Float>
                    <Float Name="Z">0.028130</Float>
                </Struct>
                <Struct Id="1">
                    <Float Name="X">142.764664</Float>
                    <Float Name="Y">89.124756</Float>
                    <Float Name="Z">0.025000</Float>
                </Struct>
                <Struct Id="1">
                    <Float Name="X">111.406128</Float>
                    <Float Name="Y">105.079788</Float>
                    <Float Name="Z">0.022560</Float>
                </Struct>
                <Struct Id="1">
                    <Float Name="X">111.405937</Float>
                    <Float Name="Y">116.082245</Float>
                    <Float Name="Z">0.025000</Float>
                </Struct>
                <Struct Id="1">
                    <Float Name="X">96.001709</Float>
                    <Float Name="Y">116.082947</Float>
                    <Float Name="Z">0.022560</Float>
                </Struct>
                <Struct Id="1">
                    <Float Name="X">95.726585</Float>
                    <Float Name="Y">105.904434</Float>
                    <Float Name="Z">0.025000</Float>
                </Struct>
                <Struct Id="1">
                    <Float Name="X">21.455956</Float>
                    <Float Name="Y">98.202286</Float>
                    <Float Name="Z">0.025000</Float>
                </Struct>
                <Struct Id="1">
                    <Float Name="X">0.000000</Float>
                    <Float Name="Y">98.477341</Float>
                    <Float Name="Z">0.025001</Float>
                </Struct>
            </List>
            <CExoLocString Name="LocalizedName">
                <DWord Name="StringRef">14510</DWord>
                <SubString>
                    <Int Name="StringID">0</Int>
                    <CExoString Name="String">Forest Encounter</CExoString>
                </SubString>
            </CExoLocString>
            <Int Name="MaxCreatures">4</Int>
            <ResRef Name="OnEntered"></ResRef>
            <ResRef Name="OnExhausted"></ResRef>
            <ResRef Name="OnExit"></ResRef>
            <ResRef Name="OnHeartbeat"></ResRef>
            <ResRef Name="OnUserDefined"></ResRef>
            <Byte Name="PlayerOnly">1</Byte>
            <Int Name="RecCreatures">2</Int>
            <Byte Name="Reset">1</Byte>
            <Int Name="ResetTime">1200</Int>
            <Int Name="Respawns">-1</Int>
            <Int Name="SpawnOption">0</Int>
            <List Name="SpawnPointList">
                <Struct Id="2">
                    <Float Name="Orientation">-0.000000</Float>
                    <Float Name="X">85.491501</Float>
                    <Float Name="Y">33.787159</Float>
                    <Float Name="Z">0.000001</Float>
                </Struct>
                <Struct Id="2">
                    <Float Name="Orientation">-0.000000</Float>
                    <Float Name="X">79.011200</Float>
                    <Float Name="Y">78.304901</Float>
                    <Float Name="Z">0.000004</Float>
                </Struct>
                <Struct Id="2">
                    <Float Name="Orientation">-0.000000</Float>
                    <Float Name="X">119.976089</Float>
                    <Float Name="Y">108.534172</Float>
                    <Float Name="Z">0.000000</Float>
                </Struct>
                <Struct Id="2">
                    <Float Name="Orientation">-0.000000</Float>
                    <Float Name="X">139.187210</Float>
                    <Float Name="Y">110.511780</Float>
                    <Float Name="Z">0.000000</Float>
                </Struct>
                <Struct Id="2">
                    <Float Name="Orientation">-0.000000</Float>
                    <Float Name="X">121.953712</Float>
                    <Float Name="Y">53.160923</Float>
                    <Float Name="Z">0.000000</Float>
                </Struct>
                <Struct Id="2">
                    <Float Name="Orientation">-0.000000</Float>
                    <Float Name="X">107.827873</Float>
                    <Float Name="Y">38.752579</Float>
                    <Float Name="Z">0.000000</Float>
                </Struct>
                <Struct Id="2">
                    <Float Name="Orientation">-0.000000</Float>
                    <Float Name="X">39.741386</Float>
                    <Float Name="Y">68.699341</Float>
                    <Float Name="Z">0.000000</Float>
                </Struct>
                <Struct Id="2">
                    <Float Name="Orientation">-0.000000</Float>
                    <Float Name="X">54.432251</Float>
                    <Float Name="Y">117.857216</Float>
                    <Float Name="Z">0.000000</Float>
                </Struct>
                <Struct Id="2">
                    <Float Name="Orientation">-0.000000</Float>
                    <Float Name="X">82.683907</Float>
                    <Float Name="Y">121.247429</Float>
                    <Float Name="Z">0.000000</Float>
                </Struct>
            </List>
            <CExoString Name="Tag">ForestEncounter</CExoString>
            <ResRef Name="TemplateResRef">slaad001</ResRef>
            <Float Name="XPosition">1.318122</Float>
            <Float Name="YPosition">40.939148</Float>
            <Float Name="ZPosition">0.000000</Float>
        </Struct>
        <Struct Id="7">
            <Byte Name="Active">1</Byte>
            <List Name="CreatureList">
                <Struct Id="0">
                    <Int Name="Appearance">35</Int>
                    <Float Name="CR">0.333333</Float>
                    <ResRef Name="ResRef">cnradeer</ResRef>
                    <Byte Name="SingleSpawn">0</Byte>
                </Struct>
                <Struct Id="0">
                    <Int Name="Appearance">37</Int>
                    <Float Name="CR">0.333333</Float>
                    <ResRef Name="ResRef">cnrawhitestag</ResRef>
                    <Byte Name="SingleSpawn">0</Byte>
                </Struct>
                <Struct Id="0">
                    <Int Name="Appearance">8</Int>
                    <Float Name="CR">0.500000</Float>
                    <ResRef Name="ResRef">cnrabadger</ResRef>
                    <Byte Name="SingleSpawn">0</Byte>
                </Struct>
                <Struct Id="0">
                    <Int Name="Appearance">12</Int>
                    <Float Name="CR">2.000000</Float>
                    <ResRef Name="ResRef">cnrablkbear</ResRef>
                    <Byte Name="SingleSpawn">0</Byte>
                </Struct>
                <Struct Id="0">
                    <Int Name="Appearance">21</Int>
                    <Float Name="CR">2.000000</Float>
                    <ResRef Name="ResRef">cnraboar</ResRef>
                    <Byte Name="SingleSpawn">0</Byte>
                </Struct>
                <Struct Id="0">
                    <Int Name="Appearance">203</Int>
                    <Float Name="CR">2.000000</Float>
                    <ResRef Name="ResRef">cnracougar</ResRef>
                    <Byte Name="SingleSpawn">0</Byte>
                </Struct>
                <Struct Id="0">
                    <Int Name="Appearance">94</Int>
                    <Float Name="CR">2.000000</Float>
                    <ResRef Name="ResRef">cnracragcat</ResRef>
                    <Byte Name="SingleSpawn">0</Byte>
                </Struct>
                <Struct Id="0">
                    <Int Name="Appearance">96</Int>
                    <Float Name="CR">2.000000</Float>
                    <ResRef Name="ResRef">nw_krenshar</ResRef>
                    <Byte Name="SingleSpawn">0</Byte>
                </Struct>
                <Struct Id="0">
                    <Int Name="Appearance">93</Int>
                    <Float Name="CR">2.000000</Float>
                    <ResRef Name="ResRef">cnraleopard</ResRef>
                    <Byte Name="SingleSpawn">0</Byte>
                </Struct>
                <Struct Id="0">
                    <Int Name="Appearance">202</Int>
                    <Float Name="CR">2.000000</Float>
                    <ResRef Name="ResRef">cnrapanther</ResRef>
                    <Byte Name="SingleSpawn">0</Byte>
                </Struct>
                <Struct Id="0">
                    <Int Name="Appearance">98</Int>
                    <Float Name="CR">3.000000</Float>
                    <ResRef Name="ResRef">cnrajaguar</ResRef>
                    <Byte Name="SingleSpawn">0</Byte>
                </Struct>
                <Struct Id="0">
                    <Int Name="Appearance">97</Int>
                    <Float Name="CR">3.000000</Float>
                    <ResRef Name="ResRef">cnralion</ResRef>
                    <Byte Name="SingleSpawn">0</Byte>
                </Struct>
                <Struct Id="0">
                    <Int Name="Appearance">13</Int>
                    <Float Name="CR">5.000000</Float>
                    <ResRef Name="ResRef">cnrabrnbear</ResRef>
                    <Byte Name="SingleSpawn">0</Byte>
                </Struct>
                <Struct Id="0">
                    <Int Name="Appearance">175</Int>
                    <Float Name="CR">5.000000</Float>
                    <ResRef Name="ResRef">nw_direwolf</ResRef>
                    <Byte Name="SingleSpawn">0</Byte>
                </Struct>
                <Struct Id="0">
                    <Int Name="Appearance">204</Int>
                    <Float Name="CR">6.000000</Float>
                    <ResRef Name="ResRef">cnragrizbear</ResRef>
                    <Byte Name="SingleSpawn">0</Byte>
                </Struct>
            </List>
            <Int Name="Difficulty">0</Int>
            <Int Name="DifficultyIndex">3</Int>
            <DWord Name="Faction">1</DWord>
            <List Name="Geometry">
                <Struct Id="1">
                    <Float Name="X">0.000000</Float>
                    <Float Name="Y">0.000000</Float>
                    <Float Name="Z">0.025000</Float>
                </Struct>
                <Struct Id="1">
                    <Float Name="X">0.825239</Float>
                    <Float Name="Y">0.000008</Float>
                    <Float Name="Z">0.025000</Float>
                </Struct>
                <Struct Id="1">
                    <Float Name="X">59.416504</Float>
                    <Float Name="Y">-24.206718</Float>
                    <Float Name="Z">0.025001</Float>
                </Struct>
                <Struct Id="1">
                    <Float Name="X">44.837456</Float>
                    <Float Name="Y">-23.931644</Float>
                    <Float Name="Z">0.025001</Float>
                </Struct>
                <Struct Id="1">
                    <Float Name="X">45.228554</Float>
                    <Float Name="Y">-37.765427</Float>
                    <Float Name="Z">0.025000</Float>
                </Struct>
                <Struct Id="1">
                    <Float Name="X">63.412926</Float>
                    <Float Name="Y">-37.613541</Float>
                    <Float Name="Z">4.025000</Float>
                </Struct>
                <Struct Id="1">
                    <Float Name="X">62.992493</Float>
                    <Float Name="Y">-23.656569</Float>
                    <Float Name="Z">0.025000</Float>
                </Struct>
                <Struct Id="1">
                    <Float Name="X">20.630730</Float>
                    <Float Name="Y">5.501530</Float>
                    <Float Name="Z">0.025000</Float>
                </Struct>
                <Struct Id="1">
                    <Float Name="X">20.080578</Float>
                    <Float Name="Y">95.726578</Float>
                    <Float Name="Z">0.025000</Float>
                </Struct>
                <Struct Id="1">
                    <Float Name="X">96.276741</Float>
                    <Float Name="Y">103.978882</Float>
                    <Float Name="Z">0.025001</Float>
                </Struct>
                <Struct Id="1">
                    <Float Name="X">108.930420</Float>
                    <Float Name="Y">103.704391</Float>
                    <Float Name="Z">0.022560</Float>
                </Struct>
                <Struct Id="1">
                    <Float Name="X">143.589890</Float>
                    <Float Name="Y">86.098900</Float>
                    <Float Name="Z">0.025000</Float>
                </Struct>
                <Struct Id="1">
                    <Float Name="X">143.864975</Float>
                    <Float Name="Y">78.671860</Float>
                    <Float Name="Z">0.025000</Float>
                </Struct>
                <Struct Id="1">
                    <Float Name="X">152.392349</Float>
                    <Float Name="Y">78.671844</Float>
                    <Float Name="Z">0.025000</Float>
                </Struct>
                <Struct Id="1">
                    <Float Name="X">152.116547</Float>
                    <Float Name="Y">89.124176</Float>
                    <Float Name="Z">0.028130</Float>
                </Struct>
                <Struct Id="1">
                    <Float Name="X">142.764664</Float>
                    <Float Name="Y">89.124756</Float>
                    <Float Name="Z">0.025000</Float>
                </Struct>
                <Struct Id="1">
                    <Float Name="X">111.406128</Float>
                    <Float Name="Y">105.079788</Float>
                    <Float Name="Z">0.022560</Float>
                </Struct>
                <Struct Id="1">
                    <Float Name="X">111.405937</Float>
                    <Float Name="Y">116.082245</Float>
                    <Float Name="Z">0.025000</Float>
                </Struct>
                <Struct Id="1">
                    <Float Name="X">96.001709</Float>
                    <Float Name="Y">116.082947</Float>
                    <Float Name="Z">0.022560</Float>
                </Struct>
                <Struct Id="1">
                    <Float Name="X">95.726585</Float>
                    <Float Name="Y">105.904434</Float>
                    <Float Name="Z">0.025000</Float>
                </Struct>
                <Struct Id="1">
                    <Float Name="X">21.455956</Float>
                    <Float Name="Y">98.202286</Float>
                    <Float Name="Z">0.025000</Float>
                </Struct>
                <Struct Id="1">
                    <Float Name="X">0.000000</Float>
                    <Float Name="Y">98.477341</Float>
                    <Float Name="Z">0.025001</Float>
                </Struct>
            </List>
            <CExoLocString Name="LocalizedName">
                <DWord Name="StringRef">14510</DWord>
                <SubString>
                    <Int Name="StringID">0</Int>
                    <CExoString Name="String">Forest Encounter</CExoString>
                </SubString>
            </CExoLocString>
            <Int Name="MaxCreatures">2</Int>
            <ResRef Name="OnEntered"></ResRef>
            <ResRef Name="OnExhausted"></ResRef>
            <ResRef Name="OnExit"></ResRef>
            <ResRef Name="OnHeartbeat"></ResRef>
            <ResRef Name="OnUserDefined"></ResRef>
            <Byte Name="PlayerOnly">1</Byte>
            <Int Name="RecCreatures">1</Int>
            <Byte Name="Reset">1</Byte>
            <Int Name="ResetTime">1200</Int>
            <Int Name="Respawns">-1</Int>
            <Int Name="SpawnOption">0</Int>
            <List Name="SpawnPointList">
                <Struct Id="2">
                    <Float Name="Orientation">-0.000000</Float>
                    <Float Name="X">108.597923</Float>
                    <Float Name="Y">45.065296</Float>
                    <Float Name="Z">0.000002</Float>
                </Struct>
                <Struct Id="2">
                    <Float Name="Orientation">-0.000000</Float>
                    <Float Name="X">70.253067</Float>
                    <Float Name="Y">132.266174</Float>
                    <Float Name="Z">-0.002441</Float>
                </Struct>
                <Struct Id="2">
                    <Float Name="Orientation">-0.000000</Float>
                    <Float Name="X">51.607082</Float>
                    <Float Name="Y">118.704765</Float>
                    <Float Name="Z">-0.000000</Float>
                </Struct>
                <Struct Id="2">
                    <Float Name="Orientation">-0.000000</Float>
                    <Float Name="X">17.421844</Float>
                    <Float Name="Y">20.388317</Float>
                    <Float Name="Z">-0.002440</Float>
                </Struct>
                <Struct Id="2">
                    <Float Name="Orientation">-0.000000</Float>
                    <Float Name="X">107.262848</Float>
                    <Float Name="Y">28.299469</Float>
                    <Float Name="Z">-0.000000</Float>
                </Struct>
                <Struct Id="2">
                    <Float Name="Orientation">-0.000000</Float>
                    <Float Name="X">128.451584</Float>
                    <Float Name="Y">60.788876</Float>
                    <Float Name="Z">-0.000000</Float>
                </Struct>
                <Struct Id="2">
                    <Float Name="Orientation">-0.000000</Float>
                    <Float Name="X">117.715958</Float>
                    <Float Name="Y">79.152451</Float>
                    <Float Name="Z">-0.000001</Float>
                </Struct>
                <Struct Id="2">
                    <Float Name="Orientation">-0.000000</Float>
                    <Float Name="X">140.599808</Float>
                    <Float Name="Y">111.641861</Float>
                    <Float Name="Z">0.000000</Float>
                </Struct>
            </List>
            <CExoString Name="Tag">ForestEncounter</CExoString>
            <ResRef Name="TemplateResRef">slaad001</ResRef>
            <Float Name="XPosition">1.318112</Float>
            <Float Name="YPosition">41.214226</Float>
            <Float Name="ZPosition">-0.000000</Float>
        </Struct>
        <Struct Id="7">
            <Byte Name="Active">1</Byte>
            <List Name="CreatureList">
                <Struct Id="0">
                    <Int Name="Appearance">144</Int>
                    <Float Name="CR">0.333333</Float>
                    <ResRef Name="ResRef">cnrafalcon</ResRef>
                    <Byte Name="SingleSpawn">0</Byte>
                </Struct>
            </List>
            <Int Name="Difficulty">0</Int>
            <Int Name="DifficultyIndex">2</Int>
            <DWord Name="Faction">1</DWord>
            <List Name="Geometry">
                <Struct Id="1">
                    <Float Name="X">-92.665421</Float>
                    <Float Name="Y">-113.854172</Float>
                    <Float Name="Z">0.025000</Float>
                </Struct>
                <Struct Id="1">
                    <Float Name="X">-92.100388</Float>
                    <Float Name="Y">-124.307289</Float>
                    <Float Name="Z">0.025000</Float>
                </Struct>
                <Struct Id="1">
                    <Float Name="X">-73.454300</Float>
                    <Float Name="Y">-124.024773</Float>
                    <Float Name="Z">0.025000</Float>
                </Struct>
                <Struct Id="1">
                    <Float Name="X">2.542664</Float>
                    <Float Name="Y">-9.040520</Float>
                    <Float Name="Z">0.025000</Float>
                </Struct>
                <Struct Id="1">
                    <Float Name="X">14.408356</Float>
                    <Float Name="Y">-9.888077</Float>
                    <Float Name="Z">0.025000</Float>
                </Struct>
                <Struct Id="1">
                    <Float Name="X">13.277237</Float>
                    <Float Name="Y">-0.000748</Float>
                    <Float Name="Z">0.028130</Float>
                </Struct>
                <Struct Id="1">
                    <Float Name="X">0.000000</Float>
                    <Float Name="Y">0.000000</Float>
                    <Float Name="Z">0.025000</Float>
                </Struct>
                <Struct Id="1">
                    <Float Name="X">1.695114</Float>
                    <Float Name="Y">-0.282532</Float>
                    <Float Name="Z">0.025000</Float>
                </Struct>
                <Struct Id="1">
                    <Float Name="X">1.130081</Float>
                    <Float Name="Y">-8.475487</Float>
                    <Float Name="Z">0.025001</Float>
                </Struct>
                <Struct Id="1">
                    <Float Name="X">-69.781578</Float>
                    <Float Name="Y">-113.854172</Float>
                    <Float Name="Z">0.025001</Float>
                </Struct>
            </List>
            <CExoLocString Name="LocalizedName">
                <DWord Name="StringRef">4294967295</DWord>
                <SubString>
                    <Int Name="StringID">0</Int>
                    <CExoString Name="String">CNR Mixed Birds</CExoString>
                </SubString>
            </CExoLocString>
            <Int Name="MaxCreatures">3</Int>
            <ResRef Name="OnEntered"></ResRef>
            <ResRef Name="OnExhausted"></ResRef>
            <ResRef Name="OnExit"></ResRef>
            <ResRef Name="OnHeartbeat"></ResRef>
            <ResRef Name="OnUserDefined"></ResRef>
            <Byte Name="PlayerOnly">1</Byte>
            <Int Name="RecCreatures">1</Int>
            <Byte Name="Reset">1</Byte>
            <Int Name="ResetTime">1200</Int>
            <Int Name="Respawns">-1</Int>
            <Int Name="SpawnOption">0</Int>
            <List Name="SpawnPointList">
                <Struct Id="2">
                    <Float Name="Orientation">-0.000000</Float>
                    <Float Name="X">126.441528</Float>
                    <Float Name="Y">52.909103</Float>
                    <Float Name="Z">0.000001</Float>
                </Struct>
                <Struct Id="2">
                    <Float Name="Orientation">-0.000000</Float>
                    <Float Name="X">96.809738</Float>
                    <Float Name="Y">70.394440</Float>
                    <Float Name="Z">0.000002</Float>
                </Struct>
                <Struct Id="2">
                    <Float Name="Orientation">-0.000000</Float>
                    <Float Name="X">100.482452</Float>
                    <Float Name="Y">86.215370</Float>
                    <Float Name="Z">0.000000</Float>
                </Struct>
                <Struct Id="2">
                    <Float Name="Orientation">-0.000000</Float>
                    <Float Name="X">119.976097</Float>
                    <Float Name="Y">105.709007</Float>
                    <Float Name="Z">0.000000</Float>
                </Struct>
                <Struct Id="2">
                    <Float Name="Orientation">-0.000000</Float>
                    <Float Name="X">53.867214</Float>
                    <Float Name="Y">106.274040</Float>
                    <Float Name="Z">0.000001</Float>
                </Struct>
                <Struct Id="2">
                    <Float Name="Orientation">-0.000000</Float>
                    <Float Name="X">62.907749</Float>
                    <Float Name="Y">49.488209</Float>
                    <Float Name="Z">0.000000</Float>
                </Struct>
            </List>
            <CExoString Name="Tag">CNRFalcons</CExoString>
            <ResRef Name="TemplateResRef">cnrmixedbirds</ResRef>
            <Float Name="XPosition">138.339661</Float>
            <Float Name="YPosition">130.005432</Float>
            <Float Name="ZPosition">0.000000</Float>
        </Struct>
        <Struct Id="7">
            <Byte Name="Active">1</Byte>
            <List Name="CreatureList">
                <Struct Id="0">
                    <Int Name="Appearance">269</Int>
                    <Float Name="CR">0.500000</Float>
                    <ResRef Name="ResRef">nw_bandit001</ResRef>
                    <Byte Name="SingleSpawn">0</Byte>
                </Struct>
                <Struct Id="0">
                    <Int Name="Appearance">257</Int>
                    <Float Name="CR">0.500000</Float>
                    <ResRef Name="ResRef">nw_bandit002</ResRef>
                    <Byte Name="SingleSpawn">0</Byte>
                </Struct>
                <Struct Id="0">
                    <Int Name="Appearance">269</Int>
                    <Float Name="CR">1.000000</Float>
                    <ResRef Name="ResRef">nw_bandit003</ResRef>
                    <Byte Name="SingleSpawn">0</Byte>
                </Struct>
                <Struct Id="0">
                    <Int Name="Appearance">269</Int>
                    <Float Name="CR">3.000000</Float>
                    <ResRef Name="ResRef">nw_bandit004</ResRef>
                    <Byte Name="SingleSpawn">0</Byte>
                </Struct>
                <Struct Id="0">
                    <Int Name="Appearance">257</Int>
                    <Float Name="CR">4.000000</Float>
                    <ResRef Name="ResRef">nw_bandit005</ResRef>
                    <Byte Name="SingleSpawn">1</Byte>
                </Struct>
            </List>
            <Int Name="Difficulty">5</Int>
            <Int Name="DifficultyIndex">3</Int>
            <DWord Name="Faction">1</DWord>
            <List Name="Geometry">
                <Struct Id="1">
                    <Float Name="X">-94.643242</Float>
                    <Float Name="Y">-16.669357</Float>
                    <Float Name="Z">0.025000</Float>
                </Struct>
                <Struct Id="1">
                    <Float Name="X">-94.361626</Float>
                    <Float Name="Y">-116.963219</Float>
                    <Float Name="Z">0.022560</Float>
                </Struct>
                <Struct Id="1">
                    <Float Name="X">-50.570648</Float>
                    <Float Name="Y">-141.541687</Float>
                    <Float Name="Z">0.025001</Float>
                </Struct>
                <Struct Id="1">
                    <Float Name="X">-50.853161</Float>
                    <Float Name="Y">-149.734680</Float>
                    <Float Name="Z">0.025000</Float>
                </Struct>
                <Struct Id="1">
                    <Float Name="X">-32.489586</Float>
                    <Float Name="Y">-149.734680</Float>
                    <Float Name="Z">0.025000</Float>
                </Struct>
                <Struct Id="1">
                    <Float Name="X">-32.489594</Float>
                    <Float Name="Y">-139.846588</Float>
                    <Float Name="Z">0.025000</Float>
                </Struct>
                <Struct Id="1">
                    <Float Name="X">-77.409721</Float>
                    <Float Name="Y">-119.787910</Float>
                    <Float Name="Z">0.025000</Float>
                </Struct>
                <Struct Id="1">
                    <Float Name="X">-75.432114</Float>
                    <Float Name="Y">-20.907104</Float>
                    <Float Name="Z">0.025001</Float>
                </Struct>
                <Struct Id="1">
                    <Float Name="X">13.560959</Float>
                    <Float Name="Y">-12.148376</Float>
                    <Float Name="Z">0.022560</Float>
                </Struct>
                <Struct Id="1">
                    <Float Name="X">16.386154</Float>
                    <Float Name="Y">-10.170715</Float>
                    <Float Name="Z">0.022560</Float>
                </Struct>
                <Struct Id="1">
                    <Float Name="X">15.820755</Float>
                    <Float Name="Y">-0.283417</Float>
                    <Float Name="Z">0.025000</Float>
                </Struct>
                <Struct Id="1">
                    <Float Name="X">0.000000</Float>
                    <Float Name="Y">0.000000</Float>
                    <Float Name="Z">0.022560</Float>
                </Struct>
                <Struct Id="1">
                    <Float Name="X">0.847359</Float>
                    <Float Name="Y">-9.888962</Float>
                    <Float Name="Z">0.025001</Float>
                </Struct>
            </List>
            <CExoLocString Name="LocalizedName">
                <DWord Name="StringRef">4294967295</DWord>
                <SubString>
                    <Int Name="StringID">0</Int>
                    <CExoString Name="String">Bandit Encounter</CExoString>
                </SubString>
            </CExoLocString>
            <Int Name="MaxCreatures">4</Int>
            <ResRef Name="OnEntered"></ResRef>
            <ResRef Name="OnExhausted"></ResRef>
            <ResRef Name="OnExit"></ResRef>
            <ResRef Name="OnHeartbeat"></ResRef>
            <ResRef Name="OnUserDefined"></ResRef>
            <Byte Name="PlayerOnly">1</Byte>
            <Int Name="RecCreatures">2</Int>
            <Byte Name="Reset">1</Byte>
            <Int Name="ResetTime">1200</Int>
            <Int Name="Respawns">-1</Int>
            <Int Name="SpawnOption">0</Int>
            <List Name="SpawnPointList">
                <Struct Id="2">
                    <Float Name="Orientation">-0.000000</Float>
                    <Float Name="X">87.048943</Float>
                    <Float Name="Y">86.937057</Float>
                    <Float Name="Z">0.000003</Float>
                </Struct>
                <Struct Id="2">
                    <Float Name="Orientation">-0.000000</Float>
                    <Float Name="X">95.679665</Float>
                    <Float Name="Y">103.731400</Float>
                    <Float Name="Z">0.000001</Float>
                </Struct>
                <Struct Id="2">
                    <Float Name="Orientation">-0.000000</Float>
                    <Float Name="X">100.199928</Float>
                    <Float Name="Y">85.085304</Float>
                    <Float Name="Z">0.000000</Float>
                </Struct>
                <Struct Id="2">
                    <Float Name="Orientation">-0.000000</Float>
                    <Float Name="X">112.065643</Float>
                    <Float Name="Y">97.516029</Float>
                    <Float Name="Z">0.000000</Float>
                </Struct>
                <Struct Id="2">
                    <Float Name="Orientation">-0.000000</Float>
                    <Float Name="X">45.956753</Float>
                    <Float Name="Y">56.833641</Float>
                    <Float Name="Z">0.000000</Float>
                </Struct>
                <Struct Id="2">
                    <Float Name="Orientation">-0.000000</Float>
                    <Float Name="X">60.647614</Float>
                    <Float Name="Y">55.703575</Float>
                    <Float Name="Z">0.000001</Float>
                </Struct>
                <Struct Id="2">
                    <Float Name="Orientation">-0.000000</Float>
                    <Float Name="X">44.544170</Float>
                    <Float Name="Y">45.532982</Float>
                    <Float Name="Z">0.000001</Float>
                </Struct>
                <Struct Id="2">
                    <Float Name="Orientation">-0.000000</Float>
                    <Float Name="X">63.755299</Float>
                    <Float Name="Y">42.990330</Float>
                    <Float Name="Z">0.000000</Float>
                </Struct>
                <Struct Id="2">
                    <Float Name="Orientation">-0.000000</Float>
                    <Float Name="X">48.499401</Float>
                    <Float Name="Y">90.735626</Float>
                    <Float Name="Z">0.000000</Float>
                </Struct>
                <Struct Id="2">
                    <Float Name="Orientation">-0.000000</Float>
                    <Float Name="X">58.670006</Float>
                    <Float Name="Y">100.906227</Float>
                    <Float Name="Z">0.000000</Float>
                </Struct>
                <Struct Id="2">
                    <Float Name="Orientation">-0.000000</Float>
                    <Float Name="X">61.212643</Float>
                    <Float Name="Y">88.475494</Float>
                    <Float Name="Z">0.000003</Float>
                </Struct>
            </List>
            <CExoString Name="Tag">BanditEncounter</CExoString>
            <ResRef Name="TemplateResRef">banditencounter</ResRef>
            <Float Name="XPosition">96.527405</Float>
            <Float Name="YPosition">156.845398</Float>
            <Float Name="ZPosition">0.000000</Float>
        </Struct>
        <Struct Id="7">
            <Byte Name="Active">1</Byte>
            <List Name="CreatureList">
                <Struct Id="0">
                    <Int Name="Appearance">144</Int>
                    <Float Name="CR">0.333333</Float>
                    <ResRef Name="ResRef">cnrafalcon</ResRef>
                    <Byte Name="SingleSpawn">0</Byte>
                </Struct>
            </List>
            <Int Name="Difficulty">0</Int>
            <Int Name="DifficultyIndex">2</Int>
            <DWord Name="Faction">1</DWord>
            <List Name="Geometry">
                <Struct Id="1">
                    <Float Name="X">-93.230667</Float>
                    <Float Name="Y">-14.126694</Float>
                    <Float Name="Z">0.025000</Float>
                </Struct>
                <Struct Id="1">
                    <Float Name="X">-92.383995</Float>
                    <Float Name="Y">-122.331085</Float>
                    <Float Name="Z">0.022560</Float>
                </Struct>
                <Struct Id="1">
                    <Float Name="X">-73.171982</Float>
                    <Float Name="Y">-123.743134</Float>
                    <Float Name="Z">0.025000</Float>
                </Struct>
                <Struct Id="1">
                    <Float Name="X">-75.149597</Float>
                    <Float Name="Y">-19.777023</Float>
                    <Float Name="Z">0.025000</Float>
                </Struct>
                <Struct Id="1">
                    <Float Name="X">0.564842</Float>
                    <Float Name="Y">-11.301544</Float>
                    <Float Name="Z">0.025000</Float>
                </Struct>
                <Struct Id="1">
                    <Float Name="X">13.560959</Float>
                    <Float Name="Y">-11.583313</Float>
                    <Float Name="Z">0.022560</Float>
                </Struct>
                <Struct Id="1">
                    <Float Name="X">48.027611</Float>
                    <Float Name="Y">-27.970016</Float>
                    <Float Name="Z">0.025001</Float>
                </Struct>
                <Struct Id="1">
                    <Float Name="X">48.027626</Float>
                    <Float Name="Y">-36.162994</Float>
                    <Float Name="Z">0.025000</Float>
                </Struct>
                <Struct Id="1">
                    <Float Name="X">55.938087</Float>
                    <Float Name="Y">-36.162994</Float>
                    <Float Name="Z">0.025000</Float>
                </Struct>
                <Struct Id="1">
                    <Float Name="X">56.502022</Float>
                    <Float Name="Y">-25.710632</Float>
                    <Float Name="Z">0.028130</Float>
                </Struct>
                <Struct Id="1">
                    <Float Name="X">47.462593</Float>
                    <Float Name="Y">-25.992386</Float>
                    <Float Name="Z">0.025000</Float>
                </Struct>
                <Struct Id="1">
                    <Float Name="X">16.103630</Float>
                    <Float Name="Y">-9.323151</Float>
                    <Float Name="Z">0.022560</Float>
                </Struct>
                <Struct Id="1">
                    <Float Name="X">15.255699</Float>
                    <Float Name="Y">0.846680</Float>
                    <Float Name="Z">0.025000</Float>
                </Struct>
                <Struct Id="1">
                    <Float Name="X">0.000000</Float>
                    <Float Name="Y">0.000000</Float>
                    <Float Name="Z">0.022560</Float>
                </Struct>
                <Struct Id="1">
                    <Float Name="X">0.565041</Float>
                    <Float Name="Y">-2.825180</Float>
                    <Float Name="Z">0.022560</Float>
                </Struct>
                <Struct Id="1">
                    <Float Name="X">-0.000191</Float>
                    <Float Name="Y">-8.476364</Float>
                    <Float Name="Z">0.025000</Float>
                </Struct>
            </List>
            <CExoLocString Name="LocalizedName">
                <DWord Name="StringRef">4294967295</DWord>
                <SubString>
                    <Int Name="StringID">0</Int>
                    <CExoString Name="String">CNR Mixed Birds</CExoString>
                </SubString>
            </CExoLocString>
            <Int Name="MaxCreatures">3</Int>
            <ResRef Name="OnEntered"></ResRef>
            <ResRef Name="OnExhausted"></ResRef>
            <ResRef Name="OnExit"></ResRef>
            <ResRef Name="OnHeartbeat"></ResRef>
            <ResRef Name="OnUserDefined"></ResRef>
            <Byte Name="PlayerOnly">1</Byte>
            <Int Name="RecCreatures">1</Int>
            <Byte Name="Reset">1</Byte>
            <Int Name="ResetTime">1200</Int>
            <Int Name="Respawns">-1</Int>
            <Int Name="SpawnOption">0</Int>
            <List Name="SpawnPointList">
                <Struct Id="2">
                    <Float Name="Orientation">-0.000000</Float>
                    <Float Name="X">118.701279</Float>
                    <Float Name="Y">82.723419</Float>
                    <Float Name="Z">0.000001</Float>
                </Struct>
                <Struct Id="2">
                    <Float Name="Orientation">-0.000000</Float>
                    <Float Name="X">68.275558</Float>
                    <Float Name="Y">74.914703</Float>
                    <Float Name="Z">0.000001</Float>
                </Struct>
                <Struct Id="2">
                    <Float Name="Orientation">-0.000000</Float>
                    <Float Name="X">54.432251</Float>
                    <Float Name="Y">117.009666</Float>
                    <Float Name="Z">0.000002</Float>
                </Struct>
                <Struct Id="2">
                    <Float Name="Orientation">-0.000000</Float>
                    <Float Name="X">123.366302</Float>
                    <Float Name="Y">132.830597</Float>
                    <Float Name="Z">0.000001</Float>
                </Struct>
                <Struct Id="2">
                    <Float Name="Orientation">-0.000000</Float>
                    <Float Name="X">139.469727</Float>
                    <Float Name="Y">111.076813</Float>
                    <Float Name="Z">0.000001</Float>
                </Struct>
                <Struct Id="2">
                    <Float Name="Orientation">-0.000000</Float>
                    <Float Name="X">119.976089</Float>
                    <Float Name="Y">39.600132</Float>
                    <Float Name="Z">0.000000</Float>
                </Struct>
                <Struct Id="2">
                    <Float Name="Orientation">-0.000000</Float>
                    <Float Name="X">98.787354</Float>
                    <Float Name="Y">46.945560</Float>
                    <Float Name="Z">0.000000</Float>
                </Struct>
                <Struct Id="2">
                    <Float Name="Orientation">-0.000000</Float>
                    <Float Name="X">80.423775</Float>
                    <Float Name="Y">21.801590</Float>
                    <Float Name="Z">0.000000</Float>
                </Struct>
                <Struct Id="2">
                    <Float Name="Orientation">-0.000000</Float>
                    <Float Name="X">39.741386</Float>
                    <Float Name="Y">52.878407</Float>
                    <Float Name="Z">0.000000</Float>
                </Struct>
                <Struct Id="2">
                    <Float Name="Orientation">-0.000000</Float>
                    <Float Name="X">42.849068</Float>
                    <Float Name="Y">80.565033</Float>
                    <Float Name="Z">-0.000000</Float>
                </Struct>
            </List>
            <CExoString Name="Tag">CNRFalcons</CExoString>
            <ResRef Name="TemplateResRef">cnrmixedbirds</ResRef>
            <Float Name="XPosition">96.809929</Float>
            <Float Name="YPosition">156.280350</Float>
            <Float Name="ZPosition">0.000000</Float>
        </Struct>
    </List>
    <List Name="List"/>
    <List Name="Placeable List">
        <Struct Id="9">
            <Byte Name="AnimationState">0</Byte>
            <DWord Name="Appearance">157</DWord>
            <Byte Name="AutoRemoveKey">0</Byte>
            <Float Name="Bearing">-0.000000</Float>
            <Byte Name="BodyBag">0</Byte>
            <Byte Name="CloseLockDC">0</Byte>
            <ResRef Name="Conversation"></ResRef>
            <Short Name="CurrentHP">10</Short>
            <CExoLocString Name="Description">
                <DWord Name="StringRef">4294967295</DWord>
                <SubString>
                    <Int Name="StringID">0</Int>
                    <CExoString Name="String">Place this object in any area where you want tracking to occur.  Set Will to the DC of tracking in this area.</CExoString>
                </SubString>
            </CExoLocString>
            <Byte Name="DisarmDC">0</Byte>
            <DWord Name="Faction">1</DWord>
            <Byte Name="Fort">5</Byte>
            <Short Name="HP">10</Short>
            <Byte Name="Hardness">5</Byte>
            <Byte Name="HasInventory">0</Byte>
            <Byte Name="Interruptable">1</Byte>
            <CExoString Name="KeyName"></CExoString>
            <Byte Name="KeyRequired">0</Byte>
            <CExoLocString Name="LocName">
                <DWord Name="StringRef">4294967295</DWord>
                <SubString>
                    <Int Name="StringID">0</Int>
                    <CExoString Name="String">Tracker</CExoString>
                </SubString>
            </CExoLocString>
            <Byte Name="Lockable">1</Byte>
            <Byte Name="Locked">0</Byte>
            <ResRef Name="OnClosed"></ResRef>
            <ResRef Name="OnDamaged"></ResRef>
            <ResRef Name="OnDeath"></ResRef>
            <ResRef Name="OnDisarm"></ResRef>
            <ResRef Name="OnHeartbeat"></ResRef>
            <ResRef Name="OnInvDisturbed"></ResRef>
            <ResRef Name="OnLock"></ResRef>
            <ResRef Name="OnMeleeAttacked"></ResRef>
            <ResRef Name="OnOpen"></ResRef>
            <ResRef Name="OnSpellCastAt"></ResRef>
            <ResRef Name="OnTrapTriggered"></ResRef>
            <ResRef Name="OnUnlock"></ResRef>
            <ResRef Name="OnUsed"></ResRef>
            <ResRef Name="OnUserDefined"></ResRef>
            <Byte Name="OpenLockDC">0</Byte>
            <Byte Name="Plot">1</Byte>
            <Word Name="PortraitId">515</Word>
            <Byte Name="Ref">0</Byte>
            <Byte Name="Static">1</Byte>
            <CExoString Name="Tag">Tracker</CExoString>
            <ResRef Name="TemplateResRef">tracker</ResRef>
            <Byte Name="TrapDetectDC">0</Byte>
            <Byte Name="TrapDetectable">1</Byte>
            <Byte Name="TrapDisarmable">1</Byte>
            <Byte Name="TrapFlag">0</Byte>
            <Byte Name="TrapOneShot">1</Byte>
            <Byte Name="TrapType">0</Byte>
            <Byte Name="Type">0</Byte>
            <Byte Name="Useable">0</Byte>
            <Byte Name="Will">15</Byte>
            <Float Name="X">3.021870</Float>
            <Float Name="Y">157.540634</Float>
            <Float Name="Z">-1.000000</Float>
        </Struct>
    </List>
    <List Name="SoundList">
        <Struct Id="6">
            <Byte Name="Active">1</Byte>
            <Byte Name="Continuous">1</Byte>
            <Float Name="Elevation">1.500000</Float>
            <DWord Name="GeneratedType">0</DWord>
            <DWord Name="Hours">0</DWord>
            <DWord Name="Interval">25000</DWord>
            <DWord Name="IntervalVrtn">5000</DWord>
            <CExoLocString Name="LocName">
                <DWord Name="StringRef">4294967295</DWord>
                <SubString>
                    <Int Name="StringID">0</Int>
                    <CExoString Name="String">Hawk Cry</CExoString>
                </SubString>
            </CExoLocString>
            <Byte Name="Looping">0</Byte>
            <Float Name="MaxDistance">10.000000</Float>
            <Float Name="MinDistance">1.000000</Float>
            <Float Name="PitchVariation">0.200000</Float>
            <Byte Name="Positional">0</Byte>
            <Byte Name="Priority">19</Byte>
            <Byte Name="Random">0</Byte>
            <Byte Name="RandomPosition">0</Byte>
            <Float Name="RandomRangeX">0.000000</Float>
            <Float Name="RandomRangeY">0.000000</Float>
            <List Name="Sounds">
                <Struct Id="0">
                    <ResRef Name="Sound">as_an_hawk1</ResRef>
                </Struct>
            </List>
            <CExoString Name="Tag">HawkCry</CExoString>
            <ResRef Name="TemplateResRef">hawkcry</ResRef>
            <Byte Name="Times">1</Byte>
            <Byte Name="Volume">127</Byte>
            <Byte Name="VolumeVrtn">0</Byte>
            <Float Name="XPosition">119.349945</Float>
            <Float Name="YPosition">64.000580</Float>
            <Float Name="ZPosition">1.500001</Float>
        </Struct>
    </List>
    <List Name="StoreList"/>
    <List Name="TriggerList">
        <Struct Id="1">
            <Byte Name="AutoRemoveKey">0</Byte>
            <Byte Name="Cursor">1</Byte>
            <Byte Name="DisarmDC">0</Byte>
            <DWord Name="Faction">1</DWord>
            <List Name="Geometry">
                <Struct Id="3">
                    <Float Name="PointX">0.000000</Float>
                    <Float Name="PointY">0.000000</Float>
                    <Float Name="PointZ">0.022560</Float>
                </Struct>
                <Struct Id="3">
                    <Float Name="PointX">0.079224</Float>
                    <Float Name="PointY">-3.882034</Float>
                    <Float Name="PointZ">0.022560</Float>
                </Struct>
                <Struct Id="3">
                    <Float Name="PointX">15.923592</Float>
                    <Float Name="PointY">-3.882507</Float>
                    <Float Name="PointZ">0.025000</Float>
                </Struct>
                <Struct Id="3">
                    <Float Name="PointX">15.923599</Float>
                    <Float Name="PointY">-0.000595</Float>
                    <Float Name="PointZ">0.025000</Float>
                </Struct>
            </List>
            <Float Name="HighlightHeight">0.000000</Float>
            <CExoString Name="KeyName"></CExoString>
            <CExoString Name="LinkedTo">WP_PlainsEToSE</CExoString>
            <Byte Name="LinkedToFlags">2</Byte>
            <Word Name="LoadScreenID">0</Word>
            <CExoLocString Name="LocalizedName">
                <DWord Name="StringRef">14760</DWord>
                <SubString>
                    <Int Name="StringID">0</Int>
                    <CExoString Name="String">New Area Transition</CExoString>
                </SubString>
            </CExoLocString>
            <ResRef Name="OnClick"></ResRef>
            <ResRef Name="OnDisarm"></ResRef>
            <ResRef Name="OnTrapTriggered"></ResRef>
            <Word Name="PortraitId">0</Word>
            <ResRef Name="ScriptHeartbeat"></ResRef>
            <ResRef Name="ScriptOnEnter"></ResRef>
            <ResRef Name="ScriptOnExit"></ResRef>
            <ResRef Name="ScriptUserDefine"></ResRef>
            <CExoString Name="Tag">PlainsSEToE</CExoString>
            <ResRef Name="TemplateResRef">newtransition</ResRef>
            <Byte Name="TrapDetectDC">0</Byte>
            <Byte Name="TrapDetectable">1</Byte>
            <Byte Name="TrapDisarmable">1</Byte>
            <Byte Name="TrapFlag">0</Byte>
            <Byte Name="TrapOneShot">1</Byte>
            <Byte Name="TrapType">0</Byte>
            <Int Name="Type">1</Int>
            <Float Name="XOrientation">0.000000</Float>
            <Float Name="XPosition">97.112907</Float>
            <Float Name="YOrientation">0.000000</Float>
            <Float Name="YPosition">159.390823</Float>
            <Float Name="ZOrientation">0.000000</Float>
            <Float Name="ZPosition">0.000000</Float>
        </Struct>
        <Struct Id="1">
            <Byte Name="AutoRemoveKey">0</Byte>
            <Byte Name="Cursor">1</Byte>
            <Byte Name="DisarmDC">0</Byte>
            <DWord Name="Faction">1</DWord>
            <List Name="Geometry">
                <Struct Id="3">
                    <Float Name="PointX">-0.122744</Float>
                    <Float Name="PointY">0.245499</Float>
                    <Float Name="PointZ">0.025000</Float>
                </Struct>
                <Struct Id="3">
                    <Float Name="PointX">0.000000</Float>
                    <Float Name="PointY">0.000000</Float>
                    <Float Name="PointZ">0.025000</Float>
                </Struct>
                <Struct Id="3">
                    <Float Name="PointX">0.000001</Float>
                    <Float Name="PointY">-52.534523</Float>
                    <Float Name="PointZ">0.025000</Float>
                </Struct>
                <Struct Id="3">
                    <Float Name="PointX">2.700373</Float>
                    <Float Name="PointY">-52.534523</Float>
                    <Float Name="PointZ">0.025000</Float>
                </Struct>
                <Struct Id="3">
                    <Float Name="PointX">2.700374</Float>
                    <Float Name="PointY">0.245499</Float>
                    <Float Name="PointZ">0.025000</Float>
                </Struct>
            </List>
            <Float Name="HighlightHeight">0.000000</Float>
            <CExoString Name="KeyName"></CExoString>
            <CExoString Name="LinkedTo"></CExoString>
            <Byte Name="LinkedToFlags">2</Byte>
            <Word Name="LoadScreenID">0</Word>
            <CExoLocString Name="LocalizedName">
                <DWord Name="StringRef">14760</DWord>
                <SubString>
                    <Int Name="StringID">0</Int>
                    <CExoString Name="String">Anph Transition</CExoString>
                </SubString>
            </CExoLocString>
            <ResRef Name="OnClick">anph_transition</ResRef>
            <ResRef Name="OnDisarm"></ResRef>
            <ResRef Name="OnTrapTriggered"></ResRef>
            <Word Name="PortraitId">0</Word>
            <ResRef Name="ScriptHeartbeat"></ResRef>
            <ResRef Name="ScriptOnEnter">anph_transition</ResRef>
            <ResRef Name="ScriptOnExit"></ResRef>
            <ResRef Name="ScriptUserDefine"></ResRef>
            <CExoString Name="Tag">PlainsSW</CExoString>
            <ResRef Name="TemplateResRef">newtransition001</ResRef>
            <Byte Name="TrapDetectDC">0</Byte>
            <Byte Name="TrapDetectable">1</Byte>
            <Byte Name="TrapDisarmable">1</Byte>
            <Byte Name="TrapFlag">0</Byte>
            <Byte Name="TrapOneShot">1</Byte>
            <Byte Name="TrapType">0</Byte>
            <Int Name="Type">1</Int>
            <Float Name="XOrientation">0.000000</Float>
            <Float Name="XPosition">0.451818</Float>
            <Float Name="YOrientation">0.000000</Float>
            <Float Name="YPosition">134.585510</Float>
            <Float Name="ZOrientation">0.000000</Float>
            <Float Name="ZPosition">0.000000</Float>
        </Struct>
        <Struct Id="1">
            <Byte Name="AutoRemoveKey">0</Byte>
            <Byte Name="Cursor">1</Byte>
            <Byte Name="DisarmDC">0</Byte>
            <DWord Name="Faction">1</DWord>
            <List Name="Geometry">
                <Struct Id="3">
                    <Float Name="PointX">-0.176213</Float>
                    <Float Name="PointY">-36.123501</Float>
                    <Float Name="PointZ">0.025000</Float>
                </Struct>
                <Struct Id="3">
                    <Float Name="PointX">2.643183</Float>
                    <Float Name="PointY">-36.123505</Float>
                    <Float Name="PointZ">0.025001</Float>
                </Struct>
                <Struct Id="3">
                    <Float Name="PointX">2.643183</Float>
                    <Float Name="PointY">0.000000</Float>
                    <Float Name="PointZ">0.025000</Float>
                </Struct>
                <Struct Id="3">
                    <Float Name="PointX">0.000000</Float>
                    <Float Name="PointY">0.000000</Float>
                    <Float Name="PointZ">0.025001</Float>
                </Struct>
                <Struct Id="3">
                    <Float Name="PointX">-0.176211</Float>
                    <Float Name="PointY">0.088112</Float>
                    <Float Name="PointZ">0.025000</Float>
                </Struct>
            </List>
            <Float Name="HighlightHeight">0.000000</Float>
            <CExoString Name="KeyName"></CExoString>
            <CExoString Name="LinkedTo"></CExoString>
            <Byte Name="LinkedToFlags">2</Byte>
            <Word Name="LoadScreenID">0</Word>
            <CExoLocString Name="LocalizedName">
                <DWord Name="StringRef">14760</DWord>
                <SubString>
                    <Int Name="StringID">0</Int>
                    <CExoString Name="String">Anph Transition</CExoString>
                </SubString>
            </CExoLocString>
            <ResRef Name="OnClick">anph_transition</ResRef>
            <ResRef Name="OnDisarm"></ResRef>
            <ResRef Name="OnTrapTriggered"></ResRef>
            <Word Name="PortraitId">0</Word>
            <ResRef Name="ScriptHeartbeat"></ResRef>
            <ResRef Name="ScriptOnEnter">anph_transition</ResRef>
            <ResRef Name="ScriptOnExit"></ResRef>
            <ResRef Name="ScriptUserDefine"></ResRef>
            <CExoString Name="Tag">PlainsSW</CExoString>
            <ResRef Name="TemplateResRef">newtransition001</ResRef>
            <Byte Name="TrapDetectDC">0</Byte>
            <Byte Name="TrapDetectable">1</Byte>
            <Byte Name="TrapDisarmable">1</Byte>
            <Byte Name="TrapFlag">0</Byte>
            <Byte Name="TrapOneShot">1</Byte>
            <Byte Name="TrapType">0</Byte>
            <Int Name="Type">1</Int>
            <Float Name="XOrientation">0.000000</Float>
            <Float Name="XPosition">0.505921</Float>
            <Float Name="YOrientation">0.000000</Float>
            <Float Name="YPosition">82.101807</Float>
            <Float Name="ZOrientation">0.000000</Float>
            <Float Name="ZPosition">0.000000</Float>
        </Struct>
    </List>
    <List Name="WaypointList">
        <Struct Id="5">
            <Byte Name="Appearance">1</Byte>
            <CExoLocString Name="Description">
                <DWord Name="StringRef">4294967295</DWord>
            </CExoLocString>
            <Byte Name="HasMapNote">0</Byte>
            <CExoString Name="LinkedTo"></CExoString>
            <CExoLocString Name="LocalizedName">
                <DWord Name="StringRef">14817</DWord>
                <SubString>
                    <Int Name="StringID">0</Int>
                    <CExoString Name="String">Waypoint</CExoString>
                </SubString>
            </CExoLocString>
            <CExoLocString Name="MapNote">
                <DWord Name="StringRef">4294967295</DWord>
            </CExoLocString>
            <Byte Name="MapNoteEnabled">1</Byte>
            <CExoString Name="Tag">PlainsSEMarker</CExoString>
            <ResRef Name="TemplateResRef">nw_waypoint001</ResRef>
            <Float Name="XOrientation">0.000000</Float>
            <Float Name="XPosition">82.573418</Float>
            <Float Name="YOrientation">1.000000</Float>
            <Float Name="YPosition">81.790215</Float>
            <Float Name="ZPosition">0.000000</Float>
        </Struct>
        <Struct Id="5">
            <Byte Name="Appearance">1</Byte>
            <CExoLocString Name="Description">
                <DWord Name="StringRef">4294967295</DWord>
            </CExoLocString>
            <Byte Name="HasMapNote">0</Byte>
            <CExoString Name="LinkedTo"></CExoString>
            <CExoLocString Name="LocalizedName">
                <DWord Name="StringRef">4294967295</DWord>
            </CExoLocString>
            <CExoLocString Name="MapNote">
                <DWord Name="StringRef">4294967295</DWord>
            </CExoLocString>
            <Byte Name="MapNoteEnabled">0</Byte>
            <CExoString Name="Tag">WP_PlainsSEToE</CExoString>
            <ResRef Name="TemplateResRef"></ResRef>
            <Float Name="XOrientation">0.049088</Float>
            <Float Name="XPosition">105.312386</Float>
            <Float Name="YOrientation">-0.998794</Float>
            <Float Name="YPosition">151.824768</Float>
            <Float Name="ZPosition">0.010002</Float>
        </Struct>
        <Struct Id="5">
            <Byte Name="Appearance">3</Byte>
            <CExoLocString Name="Description">
                <DWord Name="StringRef">4294967295</DWord>
            </CExoLocString>
            <Byte Name="HasMapNote">0</Byte>
            <CExoString Name="LinkedTo"></CExoString>
            <CExoLocString Name="LocalizedName">
                <DWord Name="StringRef">4294967295</DWord>
                <SubString>
                    <Int Name="StringID">0</Int>
                    <CExoString Name="String">BEENEST, offset 10</CExoString>
                </SubString>
            </CExoLocString>
            <CExoLocString Name="MapNote">
                <DWord Name="StringRef">4294967295</DWord>
            </CExoLocString>
            <Byte Name="MapNoteEnabled">0</Byte>
            <CExoString Name="Tag">cnr_resourcepoint</CExoString>
            <ResRef Name="TemplateResRef">cnr_resourcep097</ResRef>
            <Float Name="XOrientation">0.000000</Float>
            <Float Name="XPosition">109.997467</Float>
            <Float Name="YOrientation">1.000000</Float>
            <Float Name="YPosition">60.069756</Float>
            <Float Name="ZPosition">-0.000000</Float>
        </Struct>
        <Struct Id="5">
            <Byte Name="Appearance">3</Byte>
            <CExoLocString Name="Description">
                <DWord Name="StringRef">4294967295</DWord>
            </CExoLocString>
            <Byte Name="HasMapNote">0</Byte>
            <CExoString Name="LinkedTo"></CExoString>
            <CExoLocString Name="LocalizedName">
                <DWord Name="StringRef">4294967295</DWord>
                <SubString>
                    <Int Name="StringID">0</Int>
                    <CExoString Name="String">BEENEST, offset 10</CExoString>
                </SubString>
            </CExoLocString>
            <CExoLocString Name="MapNote">
                <DWord Name="StringRef">4294967295</DWord>
            </CExoLocString>
            <Byte Name="MapNoteEnabled">0</Byte>
            <CExoString Name="Tag">cnr_resourcepoint</CExoString>
            <ResRef Name="TemplateResRef">cnr_resourcep097</ResRef>
            <Float Name="XOrientation">0.000000</Float>
            <Float Name="XPosition">80.100410</Float>
            <Float Name="YOrientation">1.000000</Float>
            <Float Name="YPosition">39.502541</Float>
            <Float Name="ZPosition">-0.000000</Float>
        </Struct>
        <Struct Id="5">
            <Byte Name="Appearance">3</Byte>
            <CExoLocString Name="Description">
                <DWord Name="StringRef">4294967295</DWord>
            </CExoLocString>
            <Byte Name="HasMapNote">0</Byte>
            <CExoString Name="LinkedTo"></CExoString>
            <CExoLocString Name="LocalizedName">
                <DWord Name="StringRef">4294967295</DWord>
                <SubString>
                    <Int Name="StringID">0</Int>
                    <CExoString Name="String">BEENEST, offset 10</CExoString>
                </SubString>
            </CExoLocString>
            <CExoLocString Name="MapNote">
                <DWord Name="StringRef">4294967295</DWord>
            </CExoLocString>
            <Byte Name="MapNoteEnabled">0</Byte>
            <CExoString Name="Tag">cnr_resourcepoint</CExoString>
            <ResRef Name="TemplateResRef">cnr_resourcep097</ResRef>
            <Float Name="XOrientation">0.000000</Float>
            <Float Name="XPosition">90.942253</Float>
            <Float Name="YOrientation">1.000000</Float>
            <Float Name="YPosition">110.700691</Float>
            <Float Name="ZPosition">0.000000</Float>
        </Struct>
        <Struct Id="5">
            <Byte Name="Appearance">3</Byte>
            <CExoLocString Name="Description">
                <DWord Name="StringRef">4294967295</DWord>
            </CExoLocString>
            <Byte Name="HasMapNote">0</Byte>
            <CExoString Name="LinkedTo"></CExoString>
            <CExoLocString Name="LocalizedName">
                <DWord Name="StringRef">4294967295</DWord>
                <SubString>
                    <Int Name="StringID">0</Int>
                    <CExoString Name="String">BEENEST, offset 10</CExoString>
                </SubString>
            </CExoLocString>
            <CExoLocString Name="MapNote">
                <DWord Name="StringRef">4294967295</DWord>
            </CExoLocString>
            <Byte Name="MapNoteEnabled">0</Byte>
            <CExoString Name="Tag">cnr_resourcepoint</CExoString>
            <ResRef Name="TemplateResRef">cnr_resourcep097</ResRef>
            <Float Name="XOrientation">0.000000</Float>
            <Float Name="XPosition">22.819111</Float>
            <Float Name="YOrientation">1.000000</Float>
            <Float Name="YPosition">130.774704</Float>
            <Float Name="ZPosition">0.000010</Float>
        </Struct>
    </List>
</Gff>
