<Gff Version="1" Type="UTP">
    <Byte Name="AnimationState">4</Byte>
    <DWord Name="Appearance">172</DWord>
    <Byte Name="AutoRemoveKey">0</Byte>
    <Byte Name="BodyBag">0</Byte>
    <Byte Name="CloseLockDC">0</Byte>
    <CExoString Name="Comment">Shaft of Light - Red</CExoString>
    <ResRef Name="Conversation"></ResRef>
    <Short Name="CurrentHP">15</Short>
    <CExoLocString Name="Description">
        <DWord Name="StringRef">14725</DWord>
        <SubString>
            <Int Name="StringID">0</Int>
            <CExoString Name="String">A searing shaft of red light descends from some unseen place above.</CExoString>
        </SubString>
    </CExoLocString>
    <Byte Name="DisarmDC">15</Byte>
    <DWord Name="Faction">1</DWord>
    <Byte Name="Fort">16</Byte>
    <Short Name="HP">15</Short>
    <Byte Name="Hardness">5</Byte>
    <Byte Name="HasInventory">0</Byte>
    <Byte Name="Interruptable">1</Byte>
    <CExoString Name="KeyName"></CExoString>
    <Byte Name="KeyRequired">0</Byte>
    <CExoLocString Name="LocName">
        <DWord Name="StringRef">14719</DWord>
        <SubString>
            <Int Name="StringID">0</Int>
            <CExoString Name="String">Shaft of Fire</CExoString>
        </SubString>
    </CExoLocString>
    <Byte Name="Lockable">0</Byte>
    <Byte Name="Locked">0</Byte>
    <ResRef Name="OnClosed"></ResRef>
    <ResRef Name="OnDamaged"></ResRef>
    <ResRef Name="OnDeath"></ResRef>
    <ResRef Name="OnDisarm"></ResRef>
    <ResRef Name="OnHeartbeat"></ResRef>
    <ResRef Name="OnInvDisturbed"></ResRef>
    <ResRef Name="OnLock"></ResRef>
    <ResRef Name="OnMeleeAttacked"></ResRef>
    <ResRef Name="OnOpen"></ResRef>
    <ResRef Name="OnSpellCastAt"></ResRef>
    <ResRef Name="OnTrapTriggered"></ResRef>
    <ResRef Name="OnUnlock"></ResRef>
    <ResRef Name="OnUsed"></ResRef>
    <ResRef Name="OnUserDefined">eye_portshaft</ResRef>
    <Byte Name="OpenLockDC">18</Byte>
    <Byte Name="PaletteID">5</Byte>
    <Byte Name="Plot">0</Byte>
    <Word Name="PortraitId">530</Word>
    <Byte Name="Ref">0</Byte>
    <Byte Name="Static">1</Byte>
    <CExoString Name="Tag">ShaftofFire</CExoString>
    <ResRef Name="TemplateResRef">shaftoffire</ResRef>
    <Byte Name="TrapDetectDC">0</Byte>
    <Byte Name="TrapDetectable">1</Byte>
    <Byte Name="TrapDisarmable">1</Byte>
    <Byte Name="TrapFlag">0</Byte>
    <Byte Name="TrapOneShot">1</Byte>
    <Byte Name="TrapType">0</Byte>
    <Byte Name="Type">0</Byte>
    <Byte Name="Useable">0</Byte>
    <Byte Name="Will">0</Byte>
</Gff>
